<?xml version="1.0" encoding="utf-8" ?>
<extension xmlns:xsd="http://www.w3.org/2001/XMLSchema" xmlns:xsi="http://www.w3.org/2001/XMLSchema-instance">
  <id>DC7833B3-232C-41C5-817F-EAF1FCFBE970</id>
  <name>Portfolio</name>
  <refname>System.PortfolioBacklogBehavior</refname>
  <description>Portfolio level backlog and board</description>
  <last-change-date>2016-02-08T22:09:07.687Z</last-change-date>
  <process-id>D0171D51-FF84-4038-AFC1-8800AB613160</process-id>
  <typelet-type>2</typelet-type>
  <is-deleted>false</is-deleted>
  <is-abstract>true</is-abstract>
  <parent-type-refname>System.OrderedBehavior</parent-type-refname>
  <fields/>
</extension>
